[
  {
    "sn": 101,
    "name": "轻音部",
    "clubSn": 1,
    "level": 1,
    "exp": 50,
    "descLevel": "从<color=#ffff00ff>此</color>开始",
    "descLevel2": "从此开始",
    "footBallAbility": "",
    "des": "恭喜你成为己刮学园轻音部的成员！\n努力练习曲目展示自己的才华吧！",
    "award": 202701,
    "desUnlock": "可以开始轻音部练习演奏了"
  },
  {
    "sn": 102,
    "name": "轻音部",
    "clubSn": 1,
    "level": 2,
    "exp": 130,
    "descLevel": "成<color=#ffff00ff>长</color>路上",
    "descLevel2": "成长路上",
    "footBallAbility": "",
    "des": "你拿起乐器，小试牛刀，伴随着有偶尔的跑调和走音，却展现出你对音乐的天赋和渴望。",
    "award": 202702,
    "desUnlock": "解锁3首新歌曲"
  },
  {
    "sn": 103,
    "name": "轻音部",
    "clubSn": 1,
    "level": 3,
    "exp": 230,
    "descLevel": "已<color=#ffff00ff>经</color>习惯",
    "descLevel2": "已经习惯",
    "footBallAbility": "",
    "des": "你尝试把握音乐作品的氛围和结构，练习演奏稍有难度的歌曲。",
    "award": 202703,
    "desUnlock": "解锁3首新歌曲"
  },
  {
    "sn": 104,
    "name": "轻音部",
    "clubSn": 1,
    "level": 4,
    "exp": 350,
    "descLevel": "老<color=#ffff00ff>练</color>",
    "descLevel2": "老练",
    "footBallAbility": "",
    "des": "你准确地把握了音乐作品的氛围和结构，练习演奏稍有难度的歌曲。",
    "award": 202704,
    "desUnlock": "解锁3首新歌曲"
  },
  {
    "sn": 105,
    "name": "轻音部",
    "clubSn": 1,
    "level": 5,
    "exp": 510,
    "descLevel": "眼<color=#ffff00ff>疾</color>手快",
    "descLevel2": "眼疾手快",
    "footBallAbility": "",
    "des": "你熟练的指法捕捉着每一个跳跃的音符，将音乐作品的情感几乎完美地呈现给听众。",
    "award": 202705,
    "desUnlock": "解锁歌曲Last Strike"
  },
  {
    "sn": 106,
    "name": "轻音部",
    "clubSn": 1,
    "level": 6,
    "exp": 710,
    "descLevel": "指<color=#ffff00ff>尖</color>飞扬",
    "descLevel2": "指尖飞扬",
    "footBallAbility": "",
    "des": "你娴熟的指法如同乐器之上飞扬的舞步，将音乐作品的情感深度完美地呈现给听众！",
    "award": 202706,
    "desUnlock": "解锁歌曲Blooming Villain"
  },
  {
    "sn": 107,
    "name": "轻音部",
    "clubSn": 1,
    "level": 7,
    "exp": 950,
    "descLevel": "专<color=#ffff00ff>业</color>团队",
    "descLevel2": "专业团队",
    "footBallAbility": "",
    "des": "你的演奏如专业乐队一样精彩，稍微展现出自己的艺术个性。",
    "award": 202707,
    "desUnlock": "解锁歌曲Rivers In The Desert"
  },
  {
    "sn": 108,
    "name": "轻音部",
    "clubSn": 1,
    "level": 8,
    "exp": 1250,
    "descLevel": "专<color=#ffff00ff>家</color>级别",
    "descLevel2": "专家级别",
    "footBallAbility": "",
    "des": "你的演奏如业内专家一样华丽，展现出自己独特的艺术个性！",
    "award": 202708,
    "desUnlock": "解锁歌曲Life Will Change"
  },
  {
    "sn": 109,
    "name": "轻音部",
    "clubSn": 1,
    "level": 9,
    "exp": 1650,
    "descLevel": "大<color=#ffff00ff>猩</color>猩刚力罗",
    "descLevel2": "大猩猩刚力罗",
    "footBallAbility": "",
    "des": "你夸张的敲打动作和专属的高难度铺面，已是代表己刮学园轻音部最高水平的演奏怪物！",
    "award": 202709,
    "desUnlock": "解锁歌曲Fake Idol"
  },
  {
    "sn": 110,
    "name": "轻音部",
    "clubSn": 1,
    "level": 10,
    "exp": 0,
    "descLevel": "全<color=#ffff00ff>谱</color>面制霸",
    "descLevel2": "全谱面制霸",
    "footBallAbility": "",
    "des": "你不可思议的手速和融会贯通的谱面，已被认定为最接近指神的乐坛霸主！",
    "award": 202710,
    "desUnlock": "解锁歌曲Fatal Desire"
  },
  {
    "sn": 201,
    "name": "足球部",
    "clubSn": 2,
    "level": 1,
    "exp": 50,
    "descLevel": "初<color=#ffff00ff>学</color>者",
    "descLevel2": "初学者",
    "footBallAbility": "1",
    "des": "恭喜你成为己刮学园足球部的成员！\n接下来，多多参与训练活动，建立起一支强大的团队吧。",
    "award": 202711,
    "desUnlock": "可以开始足球部训练了"
  },
  {
    "sn": 202,
    "name": "足球部",
    "clubSn": 2,
    "level": 2,
    "exp": 100,
    "descLevel": "进<color=#ffff00ff>阶</color>者",
    "descLevel2": "进阶者",
    "footBallAbility": "1",
    "des": "足球运动的技能是通过练习积累的。\n积极参与活动训练，提高自身水平吧。",
    "award": 202712,
    "desUnlock": "解锁足球难度2和难度3"
  },
  {
    "sn": 203,
    "name": "足球部",
    "clubSn": 2,
    "level": 3,
    "exp": 150,
    "descLevel": "球<color=#ffff00ff>技</color>熟练者",
    "descLevel2": "球技熟练者",
    "footBallAbility": "2",
    "des": "在技术方面取得进步后，还会着重培养球队的战术意识和配合能力。\n积极参与活动训练，提高自身水平吧。",
    "award": 202713,
    "desUnlock": "解锁足球难度4；洞察能力提升至Lv.2"
  },
  {
    "sn": 204,
    "name": "足球部",
    "clubSn": 2,
    "level": 4,
    "exp": 200,
    "descLevel": "球<color=#ffff00ff>队</color>中坚",
    "descLevel2": "球队中坚",
    "footBallAbility": "3",
    "des": "随着球队能力的提升，学园将争取参加地区性的足球比赛，与其他学校的优秀球队交流切磋，提高水平。\n积极参与活动训练，准备迎接比赛吧。",
    "award": 202714,
    "desUnlock": "解锁足球难度5；洞察能力提升至Lv.3"
  },
  {
    "sn": 205,
    "name": "足球部",
    "clubSn": 2,
    "level": 5,
    "exp": 300,
    "descLevel": "赛<color=#ffff00ff>级</color>选手",
    "descLevel2": "赛级选手",
    "footBallAbility": "4",
    "des": "如果能在比赛中取得好成绩，不仅能获得荣誉感，还能提高球队的竞争力和自信心。\n积极参与训练吧。",
    "award": 202715,
    "desUnlock": "解锁足球难度6；洞察能力提升至Lv.4"
  },
  {
    "sn": 206,
    "name": "足球部",
    "clubSn": 2,
    "level": 6,
    "exp": 400,
    "descLevel": "进<color=#ffff00ff>攻</color>之星",
    "descLevel2": "进攻之星",
    "footBallAbility": "5",
    "des": "接下来的训练将会注重球队的体能训练和身体素质提升，以增强球员的耐力、速度和力量。",
    "award": 202716,
    "desUnlock": "解锁足球难度7；洞察能力提升至Lv.5"
  },
  {
    "sn": 207,
    "name": "足球部",
    "clubSn": 2,
    "level": 7,
    "exp": 500,
    "descLevel": "破<color=#ffff00ff>门</color>专家",
    "descLevel2": "破门专家",
    "footBallAbility": "6",
    "des": "学园希望球队能够建立起紧密的团队精神和团结合作的氛围，通过集体活动和团队建设来加强成员之间的默契和信任。\n积极参与训练活动吧！",
    "award": 202717,
    "desUnlock": "解锁足球难度8；洞察能力提升至Lv.6"
  },
  {
    "sn": 208,
    "name": "足球部",
    "clubSn": 2,
    "level": 8,
    "exp": 650,
    "descLevel": "赛<color=#ffff00ff>场</color>幻影",
    "descLevel2": "赛场幻影",
    "footBallAbility": "7",
    "des": "随着球队的稳定发展，学园将注重培养领导才能，鼓励球员们主动承担责任，带领球队向更高的目标迈进。",
    "award": 202718,
    "desUnlock": "洞察能力提升至Lv.7"
  },
  {
    "sn": 209,
    "name": "足球部",
    "clubSn": 2,
    "level": 9,
    "exp": 800,
    "descLevel": "神<color=#ffff00ff>射</color>手",
    "descLevel2": "神射手",
    "footBallAbility": "8",
    "des": "足球部发展逐渐稳定，学园将组织友谊赛和慈善比赛，你将代表学校为了荣誉而战。\n积极参与日常训练活动吧。",
    "award": 202719,
    "desUnlock": "洞察能力提升至Lv.8"
  },
  {
    "sn": 210,
    "name": "足球部",
    "clubSn": 2,
    "level": 10,
    "exp": 0,
    "descLevel": "传<color=#ffff00ff>奇</color>巨星",
    "descLevel2": "传奇巨星",
    "footBallAbility": "8",
    "des": "己刮学院足球队已经成为一支优秀的足球队伍，积极参与日常训练，赢得更多比赛的荣誉，树立起球队的光辉形象吧。",
    "award": 202720,
    "desUnlock": ""
  }
]