[
  {
    "sn": 1,
    "sceneSN": 2103,
    "flagSN": 7,
    "type": 1,
    "startPosition": [
      0
    ],
    "endPosition": [
      0
    ],
    "radius": 1.422,
    "triggerAction": "jump02_palace",
    "delay": 0.3,
    "length": 4.27,
    "triggerParam": ""
  },
  {
    "sn": 2,
    "sceneSN": 2103,
    "flagSN": 7,
    "type": 1,
    "startPosition": [
      0
    ],
    "endPosition": [
      0
    ],
    "radius": 1.36,
    "triggerAction": "jump02_palace",
    "delay": 0.3,
    "length": 4.89,
    "triggerParam": ""
  },
  {
    "sn": 3,
    "sceneSN": 2103,
    "flagSN": 7,
    "type": 1,
    "startPosition": [
      0
    ],
    "endPosition": [
      0
    ],
    "radius": 1.452,
    "triggerAction": "jump02_palace",
    "delay": 0.3,
    "length": 4.22,
    "triggerParam": ""
  },
  {
    "sn": 4,
    "sceneSN": 2103,
    "flagSN": 7,
    "type": 1,
    "startPosition": [
      0
    ],
    "endPosition": [
      0
    ],
    "radius": 1.478,
    "triggerAction": "jump02_palace",
    "delay": 0.3,
    "length": 4.74,
    "triggerParam": ""
  },
  {
    "sn": 5,
    "sceneSN": 2103,
    "flagSN": 7,
    "type": 0,
    "startPosition": [
      0
    ],
    "endPosition": [
      0
    ],
    "radius": 1.378,
    "triggerAction": "jump01_palace",
    "delay": 0.3,
    "length": 4.86,
    "triggerParam": ""
  },
  {
    "sn": 6,
    "sceneSN": 2103,
    "flagSN": 7,
    "type": 1,
    "startPosition": [
      0
    ],
    "endPosition": [
      0
    ],
    "radius": 1.532,
    "triggerAction": "jump02_palace",
    "delay": 0.3,
    "length": 4.55,
    "triggerParam": ""
  },
  {
    "sn": 7,
    "sceneSN": 2103,
    "flagSN": 7,
    "type": 0,
    "startPosition": [
      0
    ],
    "endPosition": [
      0
    ],
    "radius": 1.26,
    "triggerAction": "jump01_palace",
    "delay": 0.3,
    "length": 4.56,
    "triggerParam": ""
  },
  {
    "sn": 8,
    "sceneSN": 2103,
    "flagSN": 7,
    "type": 1,
    "startPosition": [
      0
    ],
    "endPosition": [
      0
    ],
    "radius": 1.653,
    "triggerAction": "jump04_palace",
    "delay": 0.3,
    "length": 3.65,
    "triggerParam": ""
  },
  {
    "sn": 9,
    "sceneSN": 2103,
    "flagSN": 7,
    "type": 0,
    "startPosition": [
      0
    ],
    "endPosition": [
      0
    ],
    "radius": 1.62,
    "triggerAction": "jump03_palace",
    "delay": 0.3,
    "length": 4.3,
    "triggerParam": ""
  },
  {
    "sn": 10,
    "sceneSN": 2103,
    "flagSN": 7,
    "type": 0,
    "startPosition": [
      0
    ],
    "endPosition": [
      0
    ],
    "radius": 0.973,
    "triggerAction": "jump02_palace",
    "delay": 0.3,
    "length": 4.04,
    "triggerParam": ""
  },
  {
    "sn": 12,
    "sceneSN": 2103,
    "flagSN": 7,
    "type": 1,
    "startPosition": [
      0
    ],
    "endPosition": [
      0
    ],
    "radius": 1.333,
    "triggerAction": "jump01_palace",
    "delay": 0.3,
    "length": 3.63,
    "triggerParam": ""
  },
  {
    "sn": 13,
    "sceneSN": 2103,
    "flagSN": 7,
    "type": 0,
    "startPosition": [
      0
    ],
    "endPosition": [
      0
    ],
    "radius": 1.235,
    "triggerAction": "jump01_palace",
    "delay": 0.3,
    "length": 4.43,
    "triggerParam": ""
  },
  {
    "sn": 14,
    "sceneSN": 2103,
    "flagSN": 7,
    "type": 1,
    "startPosition": [
      0
    ],
    "endPosition": [
      0
    ],
    "radius": 1.235,
    "triggerAction": "jump01_palace",
    "delay": 0.3,
    "length": 3.88,
    "triggerParam": ""
  },
  {
    "sn": 15,
    "sceneSN": 2103,
    "flagSN": 7,
    "type": 0,
    "startPosition": [
      0
    ],
    "endPosition": [
      0
    ],
    "radius": 1.235,
    "triggerAction": "jump01_palace",
    "delay": 0.3,
    "length": 4.56,
    "triggerParam": ""
  },
  {
    "sn": 16,
    "sceneSN": 2103,
    "flagSN": 7,
    "type": 1,
    "startPosition": [
      0
    ],
    "endPosition": [
      0
    ],
    "radius": 0.973,
    "triggerAction": "jump02_palace",
    "delay": 0.3,
    "length": 3.72,
    "triggerParam": ""
  },
  {
    "sn": 17,
    "sceneSN": 2103,
    "flagSN": 7,
    "type": 0,
    "startPosition": [
      0
    ],
    "endPosition": [
      0
    ],
    "radius": 0.973,
    "triggerAction": "jump02_palace",
    "delay": 0.3,
    "length": 3.78,
    "triggerParam": ""
  },
  {
    "sn": 18,
    "sceneSN": 2103,
    "flagSN": 7,
    "type": 1,
    "startPosition": [
      0
    ],
    "endPosition": [
      0
    ],
    "radius": 1.62,
    "triggerAction": "jump03_palace",
    "delay": 0.3,
    "length": 3.94,
    "triggerParam": ""
  },
  {
    "sn": 19,
    "sceneSN": 2103,
    "flagSN": 7,
    "type": 1,
    "startPosition": [
      0
    ],
    "endPosition": [
      0
    ],
    "radius": 1.227,
    "triggerAction": "jump01_palace",
    "delay": 0.3,
    "length": 4.52,
    "triggerParam": ""
  },
  {
    "sn": 20,
    "sceneSN": 2103,
    "flagSN": 7,
    "type": 1,
    "startPosition": [
      0
    ],
    "endPosition": [
      0
    ],
    "radius": 1.378,
    "triggerAction": "jump01_palace",
    "delay": 0.3,
    "length": 4.67,
    "triggerParam": ""
  },
  {
    "sn": 21,
    "sceneSN": 2103,
    "flagSN": 7,
    "type": 0,
    "startPosition": [
      0
    ],
    "endPosition": [
      0
    ],
    "radius": 1.378,
    "triggerAction": "jump01_palace",
    "delay": 0.3,
    "length": 5.01,
    "triggerParam": ""
  }
]