[
  {
    "sn": 101,
    "icon": "SNSpindao-shijie.png",
    "type": 1,
    "slot": [
      2129020
    ],
    "firstWarmValue": 0,
    "modelSn": "home_yiloupiaochuang",
    "ownSlots": [],
    "interactionSn": 0
  },
  {
    "sn": 201,
    "icon": "SNSpindao-shijie.png",
    "type": 2,
    "slot": [
      2129021
    ],
    "firstWarmValue": 0,
    "modelSn": "home_yilou_chaji",
    "ownSlots": [],
    "interactionSn": 2
  },
  {
    "sn": 301,
    "icon": "SNSpindao-shijie.png",
    "type": 3,
    "slot": [
      2129022
    ],
    "firstWarmValue": 0,
    "modelSn": "home_liangxi01",
    "ownSlots": [],
    "interactionSn": 3
  },
  {
    "sn": 401,
    "icon": "SNSpindao-shijie.png",
    "type": 4,
    "slot": [
      2129023
    ],
    "firstWarmValue": 0,
    "modelSn": "home_shafa",
    "ownSlots": [],
    "interactionSn": 4
  },
  {
    "sn": 501,
    "icon": "SNSpindao-shijie.png",
    "type": 5,
    "slot": [
      2129024
    ],
    "firstWarmValue": 0,
    "modelSn": "home_chuang",
    "ownSlots": [],
    "interactionSn": 5
  },
  {
    "sn": 1201,
    "icon": "SNSpindao-shijie.png",
    "type": 12,
    "slot": [
      2129001
    ],
    "firstWarmValue": 0,
    "modelSn": "plant_huapen01",
    "ownSlots": [
      2129061,
      2129062,
      2129063,
      2129064,
      2129065,
      2129066
    ],
    "interactionSn": 0
  },
  {
    "sn": 1202,
    "icon": "SNSpindao-shijie.png",
    "type": 12,
    "slot": [
      2129002
    ],
    "firstWarmValue": 0,
    "modelSn": "plant_huapen02",
    "ownSlots": [
      2129071,
      2129072,
      2129073,
      2129074
    ],
    "interactionSn": 0
  }
]