[
  {
    "sn": 400001,
    "skillSn": 40000,
    "level": 1,
    "buffGroupSn": 4000,
    "order": 0,
    "grade": 1,
    "motifSn": 1,
    "line": [
      102
    ],
    "unlock": 0
  },
  {
    "sn": 400002,
    "skillSn": 40000,
    "level": 2,
    "buffGroupSn": 4000,
    "order": 0,
    "grade": 1,
    "motifSn": 1,
    "line": [
      102
    ],
    "unlock": 0
  },
  {
    "sn": 400003,
    "skillSn": 40000,
    "level": 3,
    "buffGroupSn": 4000,
    "order": 0,
    "grade": 1,
    "motifSn": 1,
    "line": [
      102
    ],
    "unlock": 0
  },
  {
    "sn": 400011,
    "skillSn": 40001,
    "level": 1,
    "buffGroupSn": 4000,
    "order": 0,
    "grade": 1,
    "motifSn": 1,
    "line": [
      102
    ],
    "unlock": 0
  },
  {
    "sn": 400012,
    "skillSn": 40001,
    "level": 2,
    "buffGroupSn": 4000,
    "order": 0,
    "grade": 1,
    "motifSn": 1,
    "line": [
      102
    ],
    "unlock": 0
  },
  {
    "sn": 400013,
    "skillSn": 40001,
    "level": 3,
    "buffGroupSn": 4000,
    "order": 0,
    "grade": 1,
    "motifSn": 1,
    "line": [
      102
    ],
    "unlock": 0
  },
  {
    "sn": 400021,
    "skillSn": 40002,
    "level": 1,
    "buffGroupSn": 4000,
    "order": 0,
    "grade": 1,
    "motifSn": 1,
    "line": [
      102
    ],
    "unlock": 0
  },
  {
    "sn": 400022,
    "skillSn": 40002,
    "level": 2,
    "buffGroupSn": 4000,
    "order": 0,
    "grade": 1,
    "motifSn": 1,
    "line": [
      102
    ],
    "unlock": 0
  },
  {
    "sn": 400023,
    "skillSn": 40002,
    "level": 3,
    "buffGroupSn": 4000,
    "order": 0,
    "grade": 1,
    "motifSn": 1,
    "line": [
      102
    ],
    "unlock": 0
  },
  {
    "sn": 400031,
    "skillSn": 40003,
    "level": 1,
    "buffGroupSn": 4000,
    "order": 0,
    "grade": 2,
    "motifSn": 1,
    "line": [
      102
    ],
    "unlock": 0
  },
  {
    "sn": 400032,
    "skillSn": 40003,
    "level": 2,
    "buffGroupSn": 4000,
    "order": 0,
    "grade": 2,
    "motifSn": 1,
    "line": [
      102
    ],
    "unlock": 0
  },
  {
    "sn": 400041,
    "skillSn": 40004,
    "level": 1,
    "buffGroupSn": 4000,
    "order": 0,
    "grade": 2,
    "motifSn": 1,
    "line": [
      102
    ],
    "unlock": 0
  },
  {
    "sn": 400042,
    "skillSn": 40004,
    "level": 2,
    "buffGroupSn": 4000,
    "order": 0,
    "grade": 2,
    "motifSn": 1,
    "line": [
      102
    ],
    "unlock": 0
  },
  {
    "sn": 400051,
    "skillSn": 40005,
    "level": 1,
    "buffGroupSn": 4000,
    "order": 0,
    "grade": 3,
    "motifSn": 1,
    "line": [
      102
    ],
    "unlock": 0
  },
  {
    "sn": 400111,
    "skillSn": 40011,
    "level": 1,
    "buffGroupSn": 4001,
    "order": 0,
    "grade": 2,
    "motifSn": 1,
    "line": [
      102
    ],
    "unlock": 0
  },
  {
    "sn": 400112,
    "skillSn": 40011,
    "level": 2,
    "buffGroupSn": 4001,
    "order": 0,
    "grade": 2,
    "motifSn": 1,
    "line": [
      102
    ],
    "unlock": 0
  },
  {
    "sn": 400121,
    "skillSn": 40012,
    "level": 1,
    "buffGroupSn": 4001,
    "order": 0,
    "grade": 1,
    "motifSn": 1,
    "line": [
      102
    ],
    "unlock": 0
  },
  {
    "sn": 400122,
    "skillSn": 40012,
    "level": 2,
    "buffGroupSn": 4001,
    "order": 0,
    "grade": 1,
    "motifSn": 1,
    "line": [
      102
    ],
    "unlock": 0
  },
  {
    "sn": 400123,
    "skillSn": 40012,
    "level": 3,
    "buffGroupSn": 4001,
    "order": 0,
    "grade": 1,
    "motifSn": 1,
    "line": [
      102
    ],
    "unlock": 0
  },
  {
    "sn": 400131,
    "skillSn": 40013,
    "level": 1,
    "buffGroupSn": 4001,
    "order": 0,
    "grade": 1,
    "motifSn": 1,
    "line": [
      102
    ],
    "unlock": 0
  },
  {
    "sn": 400132,
    "skillSn": 40013,
    "level": 2,
    "buffGroupSn": 4001,
    "order": 0,
    "grade": 1,
    "motifSn": 1,
    "line": [
      102
    ],
    "unlock": 0
  },
  {
    "sn": 400133,
    "skillSn": 40013,
    "level": 3,
    "buffGroupSn": 4001,
    "order": 0,
    "grade": 1,
    "motifSn": 1,
    "line": [
      102
    ],
    "unlock": 0
  },
  {
    "sn": 400141,
    "skillSn": 40014,
    "level": 1,
    "buffGroupSn": 4001,
    "order": 0,
    "grade": 2,
    "motifSn": 1,
    "line": [
      102
    ],
    "unlock": 0
  },
  {
    "sn": 400142,
    "skillSn": 40014,
    "level": 2,
    "buffGroupSn": 4001,
    "order": 0,
    "grade": 2,
    "motifSn": 1,
    "line": [
      102
    ],
    "unlock": 0
  },
  {
    "sn": 400151,
    "skillSn": 40015,
    "level": 1,
    "buffGroupSn": 4001,
    "order": 0,
    "grade": 1,
    "motifSn": 1,
    "line": [
      102
    ],
    "unlock": 0
  },
  {
    "sn": 400152,
    "skillSn": 40015,
    "level": 2,
    "buffGroupSn": 4001,
    "order": 0,
    "grade": 1,
    "motifSn": 1,
    "line": [
      102
    ],
    "unlock": 0
  },
  {
    "sn": 400153,
    "skillSn": 40015,
    "level": 3,
    "buffGroupSn": 4001,
    "order": 0,
    "grade": 1,
    "motifSn": 1,
    "line": [
      102
    ],
    "unlock": 0
  },
  {
    "sn": 400181,
    "skillSn": 40018,
    "level": 1,
    "buffGroupSn": 4001,
    "order": 0,
    "grade": 3,
    "motifSn": 1,
    "line": [
      102
    ],
    "unlock": 0
  },
  {
    "sn": 400231,
    "skillSn": 40023,
    "level": 1,
    "buffGroupSn": 4002,
    "order": 29,
    "grade": 1,
    "motifSn": 1,
    "line": [
      101
    ],
    "unlock": 0
  },
  {
    "sn": 400232,
    "skillSn": 40023,
    "level": 2,
    "buffGroupSn": 4002,
    "order": 30,
    "grade": 1,
    "motifSn": 1,
    "line": [
      101
    ],
    "unlock": 0
  },
  {
    "sn": 400233,
    "skillSn": 40023,
    "level": 3,
    "buffGroupSn": 4002,
    "order": 31,
    "grade": 1,
    "motifSn": 1,
    "line": [
      101
    ],
    "unlock": 0
  },
  {
    "sn": 400241,
    "skillSn": 40024,
    "level": 1,
    "buffGroupSn": 4002,
    "order": 32,
    "grade": 1,
    "motifSn": 1,
    "line": [
      101
    ],
    "unlock": 0
  },
  {
    "sn": 400242,
    "skillSn": 40024,
    "level": 2,
    "buffGroupSn": 4002,
    "order": 33,
    "grade": 1,
    "motifSn": 1,
    "line": [
      101
    ],
    "unlock": 0
  },
  {
    "sn": 400243,
    "skillSn": 40024,
    "level": 3,
    "buffGroupSn": 4002,
    "order": 34,
    "grade": 1,
    "motifSn": 1,
    "line": [
      101
    ],
    "unlock": 0
  },
  {
    "sn": 400251,
    "skillSn": 40025,
    "level": 1,
    "buffGroupSn": 4002,
    "order": 35,
    "grade": 1,
    "motifSn": 1,
    "line": [
      101
    ],
    "unlock": 0
  },
  {
    "sn": 400252,
    "skillSn": 40025,
    "level": 2,
    "buffGroupSn": 4002,
    "order": 36,
    "grade": 1,
    "motifSn": 1,
    "line": [
      101
    ],
    "unlock": 0
  },
  {
    "sn": 400253,
    "skillSn": 40025,
    "level": 3,
    "buffGroupSn": 4002,
    "order": 37,
    "grade": 1,
    "motifSn": 1,
    "line": [
      101
    ],
    "unlock": 0
  },
  {
    "sn": 400281,
    "skillSn": 40028,
    "level": 1,
    "buffGroupSn": 4002,
    "order": 38,
    "grade": 2,
    "motifSn": 1,
    "line": [
      101
    ],
    "unlock": 0
  },
  {
    "sn": 400282,
    "skillSn": 40028,
    "level": 2,
    "buffGroupSn": 4002,
    "order": 39,
    "grade": 2,
    "motifSn": 1,
    "line": [
      101
    ],
    "unlock": 0
  },
  {
    "sn": 400291,
    "skillSn": 40029,
    "level": 1,
    "buffGroupSn": 4002,
    "order": 40,
    "grade": 2,
    "motifSn": 1,
    "line": [
      101
    ],
    "unlock": 0
  },
  {
    "sn": 400292,
    "skillSn": 40029,
    "level": 2,
    "buffGroupSn": 4002,
    "order": 41,
    "grade": 2,
    "motifSn": 1,
    "line": [
      101
    ],
    "unlock": 0
  },
  {
    "sn": 400331,
    "skillSn": 40033,
    "level": 1,
    "buffGroupSn": 4002,
    "order": 42,
    "grade": 3,
    "motifSn": 1,
    "line": [
      101
    ],
    "unlock": 0
  },
  {
    "sn": 400361,
    "skillSn": 40036,
    "level": 1,
    "buffGroupSn": 4003,
    "order": 43,
    "grade": 1,
    "motifSn": 1,
    "line": [
      101
    ],
    "unlock": 0
  },
  {
    "sn": 400362,
    "skillSn": 40036,
    "level": 2,
    "buffGroupSn": 4003,
    "order": 44,
    "grade": 1,
    "motifSn": 1,
    "line": [
      101
    ],
    "unlock": 0
  },
  {
    "sn": 400363,
    "skillSn": 40036,
    "level": 3,
    "buffGroupSn": 4003,
    "order": 45,
    "grade": 1,
    "motifSn": 1,
    "line": [
      101
    ],
    "unlock": 0
  },
  {
    "sn": 400371,
    "skillSn": 40037,
    "level": 1,
    "buffGroupSn": 4003,
    "order": 46,
    "grade": 1,
    "motifSn": 1,
    "line": [
      101
    ],
    "unlock": 0
  },
  {
    "sn": 400372,
    "skillSn": 40037,
    "level": 2,
    "buffGroupSn": 4003,
    "order": 47,
    "grade": 1,
    "motifSn": 1,
    "line": [
      101
    ],
    "unlock": 0
  },
  {
    "sn": 400373,
    "skillSn": 40037,
    "level": 3,
    "buffGroupSn": 4003,
    "order": 48,
    "grade": 1,
    "motifSn": 1,
    "line": [
      101
    ],
    "unlock": 0
  },
  {
    "sn": 400381,
    "skillSn": 40038,
    "level": 1,
    "buffGroupSn": 4003,
    "order": 49,
    "grade": 1,
    "motifSn": 1,
    "line": [
      101
    ],
    "unlock": 0
  },
  {
    "sn": 400382,
    "skillSn": 40038,
    "level": 2,
    "buffGroupSn": 4003,
    "order": 50,
    "grade": 1,
    "motifSn": 1,
    "line": [
      101
    ],
    "unlock": 0
  },
  {
    "sn": 400383,
    "skillSn": 40038,
    "level": 3,
    "buffGroupSn": 4003,
    "order": 51,
    "grade": 1,
    "motifSn": 1,
    "line": [
      101
    ],
    "unlock": 0
  },
  {
    "sn": 400391,
    "skillSn": 40039,
    "level": 1,
    "buffGroupSn": 4003,
    "order": 52,
    "grade": 2,
    "motifSn": 1,
    "line": [
      101
    ],
    "unlock": 0
  },
  {
    "sn": 400392,
    "skillSn": 40039,
    "level": 2,
    "buffGroupSn": 4003,
    "order": 53,
    "grade": 2,
    "motifSn": 1,
    "line": [
      101
    ],
    "unlock": 0
  },
  {
    "sn": 400401,
    "skillSn": 40040,
    "level": 1,
    "buffGroupSn": 4003,
    "order": 54,
    "grade": 2,
    "motifSn": 1,
    "line": [
      101
    ],
    "unlock": 0
  },
  {
    "sn": 400402,
    "skillSn": 40040,
    "level": 2,
    "buffGroupSn": 4003,
    "order": 55,
    "grade": 2,
    "motifSn": 1,
    "line": [
      101
    ],
    "unlock": 0
  },
  {
    "sn": 400411,
    "skillSn": 40041,
    "level": 1,
    "buffGroupSn": 4003,
    "order": 56,
    "grade": 3,
    "motifSn": 1,
    "line": [
      101
    ],
    "unlock": 0
  },
  {
    "sn": 400441,
    "skillSn": 40044,
    "level": 1,
    "buffGroupSn": 4004,
    "order": 57,
    "grade": 1,
    "motifSn": 1,
    "line": [
      101
    ],
    "unlock": 0
  },
  {
    "sn": 400442,
    "skillSn": 40044,
    "level": 2,
    "buffGroupSn": 4004,
    "order": 58,
    "grade": 1,
    "motifSn": 1,
    "line": [
      101
    ],
    "unlock": 0
  },
  {
    "sn": 400443,
    "skillSn": 40044,
    "level": 3,
    "buffGroupSn": 4004,
    "order": 59,
    "grade": 1,
    "motifSn": 1,
    "line": [
      101
    ],
    "unlock": 0
  },
  {
    "sn": 400451,
    "skillSn": 40045,
    "level": 1,
    "buffGroupSn": 4004,
    "order": 60,
    "grade": 1,
    "motifSn": 1,
    "line": [
      101
    ],
    "unlock": 0
  },
  {
    "sn": 400452,
    "skillSn": 40045,
    "level": 2,
    "buffGroupSn": 4004,
    "order": 61,
    "grade": 1,
    "motifSn": 1,
    "line": [
      101
    ],
    "unlock": 0
  },
  {
    "sn": 400453,
    "skillSn": 40045,
    "level": 3,
    "buffGroupSn": 4004,
    "order": 62,
    "grade": 1,
    "motifSn": 1,
    "line": [
      101
    ],
    "unlock": 0
  },
  {
    "sn": 400461,
    "skillSn": 40046,
    "level": 1,
    "buffGroupSn": 4004,
    "order": 63,
    "grade": 1,
    "motifSn": 1,
    "line": [
      101
    ],
    "unlock": 0
  },
  {
    "sn": 400462,
    "skillSn": 40046,
    "level": 2,
    "buffGroupSn": 4004,
    "order": 64,
    "grade": 1,
    "motifSn": 1,
    "line": [
      101
    ],
    "unlock": 0
  },
  {
    "sn": 400463,
    "skillSn": 40046,
    "level": 3,
    "buffGroupSn": 4004,
    "order": 65,
    "grade": 1,
    "motifSn": 1,
    "line": [
      101
    ],
    "unlock": 0
  },
  {
    "sn": 400471,
    "skillSn": 40047,
    "level": 1,
    "buffGroupSn": 4004,
    "order": 66,
    "grade": 2,
    "motifSn": 1,
    "line": [
      101
    ],
    "unlock": 0
  },
  {
    "sn": 400472,
    "skillSn": 40047,
    "level": 2,
    "buffGroupSn": 4004,
    "order": 67,
    "grade": 2,
    "motifSn": 1,
    "line": [
      101
    ],
    "unlock": 0
  },
  {
    "sn": 400501,
    "skillSn": 40050,
    "level": 1,
    "buffGroupSn": 4004,
    "order": 68,
    "grade": 2,
    "motifSn": 1,
    "line": [
      101
    ],
    "unlock": 0
  },
  {
    "sn": 400502,
    "skillSn": 40050,
    "level": 2,
    "buffGroupSn": 4004,
    "order": 69,
    "grade": 2,
    "motifSn": 1,
    "line": [
      101
    ],
    "unlock": 0
  },
  {
    "sn": 400511,
    "skillSn": 40051,
    "level": 1,
    "buffGroupSn": 4004,
    "order": 70,
    "grade": 3,
    "motifSn": 1,
    "line": [
      101
    ],
    "unlock": 0
  },
  {
    "sn": 400541,
    "skillSn": 40054,
    "level": 1,
    "buffGroupSn": 4005,
    "order": 71,
    "grade": 1,
    "motifSn": 1,
    "line": [
      101
    ],
    "unlock": 0
  },
  {
    "sn": 400542,
    "skillSn": 40054,
    "level": 2,
    "buffGroupSn": 4005,
    "order": 72,
    "grade": 1,
    "motifSn": 1,
    "line": [
      101
    ],
    "unlock": 0
  },
  {
    "sn": 400543,
    "skillSn": 40054,
    "level": 3,
    "buffGroupSn": 4005,
    "order": 73,
    "grade": 1,
    "motifSn": 1,
    "line": [
      101
    ],
    "unlock": 0
  },
  {
    "sn": 400551,
    "skillSn": 40055,
    "level": 1,
    "buffGroupSn": 4005,
    "order": 74,
    "grade": 1,
    "motifSn": 1,
    "line": [
      101
    ],
    "unlock": 0
  },
  {
    "sn": 400552,
    "skillSn": 40055,
    "level": 2,
    "buffGroupSn": 4005,
    "order": 75,
    "grade": 1,
    "motifSn": 1,
    "line": [
      101
    ],
    "unlock": 0
  },
  {
    "sn": 400553,
    "skillSn": 40055,
    "level": 3,
    "buffGroupSn": 4005,
    "order": 76,
    "grade": 1,
    "motifSn": 1,
    "line": [
      101
    ],
    "unlock": 0
  },
  {
    "sn": 400561,
    "skillSn": 40056,
    "level": 1,
    "buffGroupSn": 4005,
    "order": 77,
    "grade": 1,
    "motifSn": 1,
    "line": [
      101
    ],
    "unlock": 0
  },
  {
    "sn": 400562,
    "skillSn": 40056,
    "level": 2,
    "buffGroupSn": 4005,
    "order": 78,
    "grade": 1,
    "motifSn": 1,
    "line": [
      101
    ],
    "unlock": 0
  },
  {
    "sn": 400563,
    "skillSn": 40056,
    "level": 3,
    "buffGroupSn": 4005,
    "order": 79,
    "grade": 1,
    "motifSn": 1,
    "line": [
      101
    ],
    "unlock": 0
  },
  {
    "sn": 400571,
    "skillSn": 40057,
    "level": 1,
    "buffGroupSn": 4005,
    "order": 80,
    "grade": 2,
    "motifSn": 1,
    "line": [
      101
    ],
    "unlock": 0
  },
  {
    "sn": 400572,
    "skillSn": 40057,
    "level": 2,
    "buffGroupSn": 4005,
    "order": 81,
    "grade": 2,
    "motifSn": 1,
    "line": [
      101
    ],
    "unlock": 0
  },
  {
    "sn": 400581,
    "skillSn": 40058,
    "level": 1,
    "buffGroupSn": 4005,
    "order": 82,
    "grade": 2,
    "motifSn": 1,
    "line": [
      101
    ],
    "unlock": 0
  },
  {
    "sn": 400582,
    "skillSn": 40058,
    "level": 2,
    "buffGroupSn": 4005,
    "order": 83,
    "grade": 2,
    "motifSn": 1,
    "line": [
      101
    ],
    "unlock": 0
  },
  {
    "sn": 400611,
    "skillSn": 40061,
    "level": 1,
    "buffGroupSn": 4005,
    "order": 84,
    "grade": 3,
    "motifSn": 1,
    "line": [
      101
    ],
    "unlock": 0
  },
  {
    "sn": 400621,
    "skillSn": 40062,
    "level": 1,
    "buffGroupSn": 4006,
    "order": 85,
    "grade": 1,
    "motifSn": 1,
    "line": [
      101
    ],
    "unlock": 0
  },
  {
    "sn": 400622,
    "skillSn": 40062,
    "level": 2,
    "buffGroupSn": 4006,
    "order": 86,
    "grade": 1,
    "motifSn": 1,
    "line": [
      101
    ],
    "unlock": 0
  },
  {
    "sn": 400623,
    "skillSn": 40062,
    "level": 3,
    "buffGroupSn": 4006,
    "order": 87,
    "grade": 1,
    "motifSn": 1,
    "line": [
      101
    ],
    "unlock": 0
  },
  {
    "sn": 400631,
    "skillSn": 40063,
    "level": 1,
    "buffGroupSn": 4006,
    "order": 88,
    "grade": 1,
    "motifSn": 1,
    "line": [
      101
    ],
    "unlock": 0
  },
  {
    "sn": 400632,
    "skillSn": 40063,
    "level": 2,
    "buffGroupSn": 4006,
    "order": 89,
    "grade": 1,
    "motifSn": 1,
    "line": [
      101
    ],
    "unlock": 0
  },
  {
    "sn": 400633,
    "skillSn": 40063,
    "level": 3,
    "buffGroupSn": 4006,
    "order": 90,
    "grade": 1,
    "motifSn": 1,
    "line": [
      101
    ],
    "unlock": 0
  },
  {
    "sn": 400641,
    "skillSn": 40064,
    "level": 1,
    "buffGroupSn": 4006,
    "order": 91,
    "grade": 1,
    "motifSn": 1,
    "line": [
      101
    ],
    "unlock": 0
  },
  {
    "sn": 400642,
    "skillSn": 40064,
    "level": 2,
    "buffGroupSn": 4006,
    "order": 92,
    "grade": 1,
    "motifSn": 1,
    "line": [
      101
    ],
    "unlock": 0
  },
  {
    "sn": 400643,
    "skillSn": 40064,
    "level": 3,
    "buffGroupSn": 4006,
    "order": 93,
    "grade": 1,
    "motifSn": 1,
    "line": [
      101
    ],
    "unlock": 0
  },
  {
    "sn": 400651,
    "skillSn": 40065,
    "level": 1,
    "buffGroupSn": 4006,
    "order": 94,
    "grade": 2,
    "motifSn": 1,
    "line": [
      101
    ],
    "unlock": 0
  },
  {
    "sn": 400652,
    "skillSn": 40065,
    "level": 2,
    "buffGroupSn": 4006,
    "order": 95,
    "grade": 2,
    "motifSn": 1,
    "line": [
      101
    ],
    "unlock": 0
  },
  {
    "sn": 400661,
    "skillSn": 40066,
    "level": 1,
    "buffGroupSn": 4006,
    "order": 96,
    "grade": 2,
    "motifSn": 1,
    "line": [
      101
    ],
    "unlock": 0
  },
  {
    "sn": 400662,
    "skillSn": 40066,
    "level": 2,
    "buffGroupSn": 4006,
    "order": 97,
    "grade": 2,
    "motifSn": 1,
    "line": [
      101
    ],
    "unlock": 0
  },
  {
    "sn": 400671,
    "skillSn": 40067,
    "level": 1,
    "buffGroupSn": 4006,
    "order": 98,
    "grade": 3,
    "motifSn": 1,
    "line": [
      101
    ],
    "unlock": 0
  },
  {
    "sn": 400821,
    "skillSn": 40082,
    "level": 1,
    "buffGroupSn": 4008,
    "order": 113,
    "grade": 1,
    "motifSn": 1,
    "line": [
      101
    ],
    "unlock": 0
  },
  {
    "sn": 400822,
    "skillSn": 40082,
    "level": 2,
    "buffGroupSn": 4008,
    "order": 114,
    "grade": 1,
    "motifSn": 1,
    "line": [
      101
    ],
    "unlock": 0
  },
  {
    "sn": 400823,
    "skillSn": 40082,
    "level": 3,
    "buffGroupSn": 4008,
    "order": 115,
    "grade": 1,
    "motifSn": 1,
    "line": [
      101
    ],
    "unlock": 0
  },
  {
    "sn": 400831,
    "skillSn": 40083,
    "level": 1,
    "buffGroupSn": 4008,
    "order": 116,
    "grade": 1,
    "motifSn": 1,
    "line": [
      101
    ],
    "unlock": 0
  },
  {
    "sn": 400832,
    "skillSn": 40083,
    "level": 2,
    "buffGroupSn": 4008,
    "order": 117,
    "grade": 1,
    "motifSn": 1,
    "line": [
      101
    ],
    "unlock": 0
  },
  {
    "sn": 400833,
    "skillSn": 40083,
    "level": 3,
    "buffGroupSn": 4008,
    "order": 118,
    "grade": 1,
    "motifSn": 1,
    "line": [
      101
    ],
    "unlock": 0
  },
  {
    "sn": 400841,
    "skillSn": 40084,
    "level": 1,
    "buffGroupSn": 4008,
    "order": 122,
    "grade": 2,
    "motifSn": 1,
    "line": [
      101
    ],
    "unlock": 0
  },
  {
    "sn": 400842,
    "skillSn": 40084,
    "level": 2,
    "buffGroupSn": 4008,
    "order": 123,
    "grade": 2,
    "motifSn": 1,
    "line": [
      101
    ],
    "unlock": 0
  },
  {
    "sn": 400851,
    "skillSn": 40085,
    "level": 1,
    "buffGroupSn": 4008,
    "order": 119,
    "grade": 1,
    "motifSn": 1,
    "line": [
      101
    ],
    "unlock": 0
  },
  {
    "sn": 400852,
    "skillSn": 40085,
    "level": 2,
    "buffGroupSn": 4008,
    "order": 120,
    "grade": 1,
    "motifSn": 1,
    "line": [
      101
    ],
    "unlock": 0
  },
  {
    "sn": 400853,
    "skillSn": 40085,
    "level": 3,
    "buffGroupSn": 4008,
    "order": 121,
    "grade": 1,
    "motifSn": 1,
    "line": [
      101
    ],
    "unlock": 0
  },
  {
    "sn": 400861,
    "skillSn": 40086,
    "level": 1,
    "buffGroupSn": 4008,
    "order": 124,
    "grade": 2,
    "motifSn": 1,
    "line": [
      101
    ],
    "unlock": 0
  },
  {
    "sn": 400862,
    "skillSn": 40086,
    "level": 2,
    "buffGroupSn": 4008,
    "order": 125,
    "grade": 2,
    "motifSn": 1,
    "line": [
      101
    ],
    "unlock": 0
  },
  {
    "sn": 400871,
    "skillSn": 40087,
    "level": 1,
    "buffGroupSn": 4008,
    "order": 126,
    "grade": 3,
    "motifSn": 1,
    "line": [
      101
    ],
    "unlock": 0
  },
  {
    "sn": 400931,
    "skillSn": 40093,
    "level": 1,
    "buffGroupSn": 4009,
    "order": 0,
    "grade": 1,
    "motifSn": 1,
    "line": [
      102
    ],
    "unlock": 0
  },
  {
    "sn": 400932,
    "skillSn": 40093,
    "level": 2,
    "buffGroupSn": 4009,
    "order": 0,
    "grade": 1,
    "motifSn": 1,
    "line": [
      102
    ],
    "unlock": 0
  },
  {
    "sn": 400933,
    "skillSn": 40093,
    "level": 3,
    "buffGroupSn": 4009,
    "order": 0,
    "grade": 1,
    "motifSn": 1,
    "line": [
      102
    ],
    "unlock": 0
  },
  {
    "sn": 400941,
    "skillSn": 40094,
    "level": 1,
    "buffGroupSn": 4009,
    "order": 0,
    "grade": 1,
    "motifSn": 1,
    "line": [
      102
    ],
    "unlock": 0
  },
  {
    "sn": 400942,
    "skillSn": 40094,
    "level": 2,
    "buffGroupSn": 4009,
    "order": 0,
    "grade": 1,
    "motifSn": 1,
    "line": [
      102
    ],
    "unlock": 0
  },
  {
    "sn": 400943,
    "skillSn": 40094,
    "level": 3,
    "buffGroupSn": 4009,
    "order": 0,
    "grade": 1,
    "motifSn": 1,
    "line": [
      102
    ],
    "unlock": 0
  },
  {
    "sn": 400951,
    "skillSn": 40095,
    "level": 1,
    "buffGroupSn": 4009,
    "order": 0,
    "grade": 1,
    "motifSn": 1,
    "line": [
      102
    ],
    "unlock": 0
  },
  {
    "sn": 400952,
    "skillSn": 40095,
    "level": 2,
    "buffGroupSn": 4009,
    "order": 0,
    "grade": 1,
    "motifSn": 1,
    "line": [
      102
    ],
    "unlock": 0
  },
  {
    "sn": 400953,
    "skillSn": 40095,
    "level": 3,
    "buffGroupSn": 4009,
    "order": 0,
    "grade": 1,
    "motifSn": 1,
    "line": [
      102
    ],
    "unlock": 0
  },
  {
    "sn": 400961,
    "skillSn": 40096,
    "level": 1,
    "buffGroupSn": 4009,
    "order": 0,
    "grade": 2,
    "motifSn": 1,
    "line": [
      102
    ],
    "unlock": 0
  },
  {
    "sn": 400962,
    "skillSn": 40096,
    "level": 2,
    "buffGroupSn": 4009,
    "order": 0,
    "grade": 2,
    "motifSn": 1,
    "line": [
      102
    ],
    "unlock": 0
  },
  {
    "sn": 400971,
    "skillSn": 40097,
    "level": 1,
    "buffGroupSn": 4009,
    "order": 0,
    "grade": 2,
    "motifSn": 1,
    "line": [
      102
    ],
    "unlock": 0
  },
  {
    "sn": 400972,
    "skillSn": 40097,
    "level": 2,
    "buffGroupSn": 4009,
    "order": 0,
    "grade": 2,
    "motifSn": 1,
    "line": [
      102
    ],
    "unlock": 0
  },
  {
    "sn": 400981,
    "skillSn": 40098,
    "level": 1,
    "buffGroupSn": 4009,
    "order": 0,
    "grade": 3,
    "motifSn": 1,
    "line": [
      102
    ],
    "unlock": 0
  },
  {
    "sn": 401011,
    "skillSn": 40101,
    "level": 1,
    "buffGroupSn": 4010,
    "order": 0,
    "grade": 1,
    "motifSn": 1,
    "line": [
      102
    ],
    "unlock": 0
  },
  {
    "sn": 401012,
    "skillSn": 40101,
    "level": 2,
    "buffGroupSn": 4010,
    "order": 0,
    "grade": 1,
    "motifSn": 1,
    "line": [
      102
    ],
    "unlock": 0
  },
  {
    "sn": 401013,
    "skillSn": 40101,
    "level": 3,
    "buffGroupSn": 4010,
    "order": 0,
    "grade": 1,
    "motifSn": 1,
    "line": [
      102
    ],
    "unlock": 0
  },
  {
    "sn": 401021,
    "skillSn": 40102,
    "level": 1,
    "buffGroupSn": 4010,
    "order": 0,
    "grade": 1,
    "motifSn": 1,
    "line": [
      102
    ],
    "unlock": 0
  },
  {
    "sn": 401022,
    "skillSn": 40102,
    "level": 2,
    "buffGroupSn": 4010,
    "order": 0,
    "grade": 1,
    "motifSn": 1,
    "line": [
      102
    ],
    "unlock": 0
  },
  {
    "sn": 401023,
    "skillSn": 40102,
    "level": 3,
    "buffGroupSn": 4010,
    "order": 0,
    "grade": 1,
    "motifSn": 1,
    "line": [
      102
    ],
    "unlock": 0
  },
  {
    "sn": 401031,
    "skillSn": 40103,
    "level": 1,
    "buffGroupSn": 4010,
    "order": 0,
    "grade": 1,
    "motifSn": 1,
    "line": [
      102
    ],
    "unlock": 0
  },
  {
    "sn": 401032,
    "skillSn": 40103,
    "level": 2,
    "buffGroupSn": 4010,
    "order": 0,
    "grade": 1,
    "motifSn": 1,
    "line": [
      102
    ],
    "unlock": 0
  },
  {
    "sn": 401033,
    "skillSn": 40103,
    "level": 3,
    "buffGroupSn": 4010,
    "order": 0,
    "grade": 1,
    "motifSn": 1,
    "line": [
      102
    ],
    "unlock": 0
  },
  {
    "sn": 401041,
    "skillSn": 40104,
    "level": 1,
    "buffGroupSn": 4010,
    "order": 0,
    "grade": 2,
    "motifSn": 1,
    "line": [
      102
    ],
    "unlock": 0
  },
  {
    "sn": 401042,
    "skillSn": 40104,
    "level": 2,
    "buffGroupSn": 4010,
    "order": 0,
    "grade": 2,
    "motifSn": 1,
    "line": [
      102
    ],
    "unlock": 0
  },
  {
    "sn": 401051,
    "skillSn": 40105,
    "level": 1,
    "buffGroupSn": 4010,
    "order": 0,
    "grade": 2,
    "motifSn": 1,
    "line": [
      102
    ],
    "unlock": 0
  },
  {
    "sn": 401052,
    "skillSn": 40105,
    "level": 2,
    "buffGroupSn": 4010,
    "order": 0,
    "grade": 2,
    "motifSn": 1,
    "line": [
      102
    ],
    "unlock": 0
  },
  {
    "sn": 401081,
    "skillSn": 40108,
    "level": 1,
    "buffGroupSn": 4010,
    "order": 0,
    "grade": 3,
    "motifSn": 1,
    "line": [
      102
    ],
    "unlock": 0
  },
  {
    "sn": 401111,
    "skillSn": 40111,
    "level": 1,
    "buffGroupSn": 4011,
    "order": 0,
    "grade": 1,
    "motifSn": 1,
    "line": [
      102
    ],
    "unlock": 0
  },
  {
    "sn": 401112,
    "skillSn": 40111,
    "level": 2,
    "buffGroupSn": 4011,
    "order": 0,
    "grade": 1,
    "motifSn": 1,
    "line": [
      102
    ],
    "unlock": 0
  },
  {
    "sn": 401113,
    "skillSn": 40111,
    "level": 3,
    "buffGroupSn": 4011,
    "order": 0,
    "grade": 1,
    "motifSn": 1,
    "line": [
      102
    ],
    "unlock": 0
  },
  {
    "sn": 401121,
    "skillSn": 40112,
    "level": 1,
    "buffGroupSn": 4011,
    "order": 0,
    "grade": 1,
    "motifSn": 1,
    "line": [
      102
    ],
    "unlock": 0
  },
  {
    "sn": 401122,
    "skillSn": 40112,
    "level": 2,
    "buffGroupSn": 4011,
    "order": 0,
    "grade": 1,
    "motifSn": 1,
    "line": [
      102
    ],
    "unlock": 0
  },
  {
    "sn": 401123,
    "skillSn": 40112,
    "level": 3,
    "buffGroupSn": 4011,
    "order": 0,
    "grade": 1,
    "motifSn": 1,
    "line": [
      102
    ],
    "unlock": 0
  },
  {
    "sn": 401131,
    "skillSn": 40113,
    "level": 1,
    "buffGroupSn": 4011,
    "order": 0,
    "grade": 1,
    "motifSn": 1,
    "line": [
      102
    ],
    "unlock": 0
  },
  {
    "sn": 401132,
    "skillSn": 40113,
    "level": 2,
    "buffGroupSn": 4011,
    "order": 0,
    "grade": 1,
    "motifSn": 1,
    "line": [
      102
    ],
    "unlock": 0
  },
  {
    "sn": 401133,
    "skillSn": 40113,
    "level": 3,
    "buffGroupSn": 4011,
    "order": 0,
    "grade": 1,
    "motifSn": 1,
    "line": [
      102
    ],
    "unlock": 0
  },
  {
    "sn": 401141,
    "skillSn": 40114,
    "level": 1,
    "buffGroupSn": 4011,
    "order": 0,
    "grade": 2,
    "motifSn": 1,
    "line": [
      102
    ],
    "unlock": 0
  },
  {
    "sn": 401142,
    "skillSn": 40114,
    "level": 2,
    "buffGroupSn": 4011,
    "order": 0,
    "grade": 2,
    "motifSn": 1,
    "line": [
      102
    ],
    "unlock": 0
  },
  {
    "sn": 401151,
    "skillSn": 40115,
    "level": 1,
    "buffGroupSn": 4011,
    "order": 0,
    "grade": 2,
    "motifSn": 1,
    "line": [
      102
    ],
    "unlock": 0
  },
  {
    "sn": 401152,
    "skillSn": 40115,
    "level": 2,
    "buffGroupSn": 4011,
    "order": 0,
    "grade": 2,
    "motifSn": 1,
    "line": [
      102
    ],
    "unlock": 0
  },
  {
    "sn": 401181,
    "skillSn": 40118,
    "level": 1,
    "buffGroupSn": 4011,
    "order": 0,
    "grade": 3,
    "motifSn": 1,
    "line": [
      102
    ],
    "unlock": 0
  },
  {
    "sn": 401211,
    "skillSn": 40121,
    "level": 1,
    "buffGroupSn": 4012,
    "order": 0,
    "grade": 1,
    "motifSn": 1,
    "line": [
      102
    ],
    "unlock": 0
  },
  {
    "sn": 401212,
    "skillSn": 40121,
    "level": 2,
    "buffGroupSn": 4012,
    "order": 0,
    "grade": 1,
    "motifSn": 1,
    "line": [
      102
    ],
    "unlock": 0
  },
  {
    "sn": 401213,
    "skillSn": 40121,
    "level": 3,
    "buffGroupSn": 4012,
    "order": 0,
    "grade": 1,
    "motifSn": 1,
    "line": [
      102
    ],
    "unlock": 0
  },
  {
    "sn": 401221,
    "skillSn": 40122,
    "level": 1,
    "buffGroupSn": 4012,
    "order": 0,
    "grade": 1,
    "motifSn": 1,
    "line": [
      102
    ],
    "unlock": 0
  },
  {
    "sn": 401222,
    "skillSn": 40122,
    "level": 2,
    "buffGroupSn": 4012,
    "order": 0,
    "grade": 1,
    "motifSn": 1,
    "line": [
      102
    ],
    "unlock": 0
  },
  {
    "sn": 401223,
    "skillSn": 40122,
    "level": 3,
    "buffGroupSn": 4012,
    "order": 0,
    "grade": 1,
    "motifSn": 1,
    "line": [
      102
    ],
    "unlock": 0
  },
  {
    "sn": 401231,
    "skillSn": 40123,
    "level": 1,
    "buffGroupSn": 4012,
    "order": 0,
    "grade": 1,
    "motifSn": 1,
    "line": [
      102
    ],
    "unlock": 0
  },
  {
    "sn": 401232,
    "skillSn": 40123,
    "level": 2,
    "buffGroupSn": 4012,
    "order": 0,
    "grade": 1,
    "motifSn": 1,
    "line": [
      102
    ],
    "unlock": 0
  },
  {
    "sn": 401233,
    "skillSn": 40123,
    "level": 3,
    "buffGroupSn": 4012,
    "order": 0,
    "grade": 1,
    "motifSn": 1,
    "line": [
      102
    ],
    "unlock": 0
  },
  {
    "sn": 401241,
    "skillSn": 40124,
    "level": 1,
    "buffGroupSn": 4012,
    "order": 0,
    "grade": 2,
    "motifSn": 1,
    "line": [
      102
    ],
    "unlock": 0
  },
  {
    "sn": 401242,
    "skillSn": 40124,
    "level": 2,
    "buffGroupSn": 4012,
    "order": 0,
    "grade": 2,
    "motifSn": 1,
    "line": [
      102
    ],
    "unlock": 0
  },
  {
    "sn": 401251,
    "skillSn": 40125,
    "level": 1,
    "buffGroupSn": 4012,
    "order": 0,
    "grade": 2,
    "motifSn": 1,
    "line": [
      102
    ],
    "unlock": 0
  },
  {
    "sn": 401252,
    "skillSn": 40125,
    "level": 2,
    "buffGroupSn": 4012,
    "order": 0,
    "grade": 2,
    "motifSn": 1,
    "line": [
      102
    ],
    "unlock": 0
  },
  {
    "sn": 401261,
    "skillSn": 40126,
    "level": 1,
    "buffGroupSn": 4012,
    "order": 0,
    "grade": 3,
    "motifSn": 1,
    "line": [
      102
    ],
    "unlock": 0
  },
  {
    "sn": 401291,
    "skillSn": 40129,
    "level": 1,
    "buffGroupSn": 4013,
    "order": 0,
    "grade": 1,
    "motifSn": 1,
    "line": [
      102
    ],
    "unlock": 0
  },
  {
    "sn": 401292,
    "skillSn": 40129,
    "level": 2,
    "buffGroupSn": 4013,
    "order": 0,
    "grade": 1,
    "motifSn": 1,
    "line": [
      102
    ],
    "unlock": 0
  },
  {
    "sn": 401293,
    "skillSn": 40129,
    "level": 3,
    "buffGroupSn": 4013,
    "order": 0,
    "grade": 1,
    "motifSn": 1,
    "line": [
      102
    ],
    "unlock": 0
  },
  {
    "sn": 401301,
    "skillSn": 40130,
    "level": 1,
    "buffGroupSn": 4013,
    "order": 0,
    "grade": 1,
    "motifSn": 1,
    "line": [
      102
    ],
    "unlock": 0
  },
  {
    "sn": 401302,
    "skillSn": 40130,
    "level": 2,
    "buffGroupSn": 4013,
    "order": 0,
    "grade": 1,
    "motifSn": 1,
    "line": [
      102
    ],
    "unlock": 0
  },
  {
    "sn": 401303,
    "skillSn": 40130,
    "level": 3,
    "buffGroupSn": 4013,
    "order": 0,
    "grade": 1,
    "motifSn": 1,
    "line": [
      102
    ],
    "unlock": 0
  },
  {
    "sn": 401311,
    "skillSn": 40131,
    "level": 1,
    "buffGroupSn": 4013,
    "order": 0,
    "grade": 1,
    "motifSn": 1,
    "line": [
      102
    ],
    "unlock": 0
  },
  {
    "sn": 401312,
    "skillSn": 40131,
    "level": 2,
    "buffGroupSn": 4013,
    "order": 0,
    "grade": 1,
    "motifSn": 1,
    "line": [
      102
    ],
    "unlock": 0
  },
  {
    "sn": 401313,
    "skillSn": 40131,
    "level": 3,
    "buffGroupSn": 4013,
    "order": 0,
    "grade": 1,
    "motifSn": 1,
    "line": [
      102
    ],
    "unlock": 0
  },
  {
    "sn": 401321,
    "skillSn": 40132,
    "level": 1,
    "buffGroupSn": 4013,
    "order": 0,
    "grade": 2,
    "motifSn": 1,
    "line": [
      102
    ],
    "unlock": 0
  },
  {
    "sn": 401322,
    "skillSn": 40132,
    "level": 2,
    "buffGroupSn": 4013,
    "order": 0,
    "grade": 2,
    "motifSn": 1,
    "line": [
      102
    ],
    "unlock": 0
  },
  {
    "sn": 401331,
    "skillSn": 40133,
    "level": 1,
    "buffGroupSn": 4013,
    "order": 0,
    "grade": 2,
    "motifSn": 1,
    "line": [
      102
    ],
    "unlock": 0
  },
  {
    "sn": 401332,
    "skillSn": 40133,
    "level": 2,
    "buffGroupSn": 4013,
    "order": 0,
    "grade": 2,
    "motifSn": 1,
    "line": [
      102
    ],
    "unlock": 0
  },
  {
    "sn": 401361,
    "skillSn": 40136,
    "level": 1,
    "buffGroupSn": 4013,
    "order": 0,
    "grade": 3,
    "motifSn": 1,
    "line": [
      102
    ],
    "unlock": 0
  },
  {
    "sn": 401431,
    "skillSn": 40143,
    "level": 1,
    "buffGroupSn": 4014,
    "order": 0,
    "grade": 1,
    "motifSn": 1,
    "line": [
      102
    ],
    "unlock": 0
  },
  {
    "sn": 401432,
    "skillSn": 40143,
    "level": 2,
    "buffGroupSn": 4014,
    "order": 0,
    "grade": 1,
    "motifSn": 1,
    "line": [
      102
    ],
    "unlock": 0
  },
  {
    "sn": 401433,
    "skillSn": 40143,
    "level": 3,
    "buffGroupSn": 4014,
    "order": 0,
    "grade": 1,
    "motifSn": 1,
    "line": [
      102
    ],
    "unlock": 0
  },
  {
    "sn": 401441,
    "skillSn": 40144,
    "level": 1,
    "buffGroupSn": 4014,
    "order": 0,
    "grade": 1,
    "motifSn": 1,
    "line": [
      102
    ],
    "unlock": 0
  },
  {
    "sn": 401442,
    "skillSn": 40144,
    "level": 2,
    "buffGroupSn": 4014,
    "order": 0,
    "grade": 1,
    "motifSn": 1,
    "line": [
      102
    ],
    "unlock": 0
  },
  {
    "sn": 401443,
    "skillSn": 40144,
    "level": 3,
    "buffGroupSn": 4014,
    "order": 0,
    "grade": 1,
    "motifSn": 1,
    "line": [
      102
    ],
    "unlock": 0
  },
  {
    "sn": 401451,
    "skillSn": 40145,
    "level": 1,
    "buffGroupSn": 4014,
    "order": 0,
    "grade": 1,
    "motifSn": 1,
    "line": [
      102
    ],
    "unlock": 0
  },
  {
    "sn": 401452,
    "skillSn": 40145,
    "level": 2,
    "buffGroupSn": 4014,
    "order": 0,
    "grade": 1,
    "motifSn": 1,
    "line": [
      102
    ],
    "unlock": 0
  },
  {
    "sn": 401453,
    "skillSn": 40145,
    "level": 3,
    "buffGroupSn": 4014,
    "order": 0,
    "grade": 1,
    "motifSn": 1,
    "line": [
      102
    ],
    "unlock": 0
  },
  {
    "sn": 401461,
    "skillSn": 40146,
    "level": 1,
    "buffGroupSn": 4014,
    "order": 0,
    "grade": 2,
    "motifSn": 1,
    "line": [
      102
    ],
    "unlock": 0
  },
  {
    "sn": 401462,
    "skillSn": 40146,
    "level": 2,
    "buffGroupSn": 4014,
    "order": 0,
    "grade": 2,
    "motifSn": 1,
    "line": [
      102
    ],
    "unlock": 0
  },
  {
    "sn": 401471,
    "skillSn": 40147,
    "level": 1,
    "buffGroupSn": 4014,
    "order": 0,
    "grade": 2,
    "motifSn": 1,
    "line": [
      102
    ],
    "unlock": 0
  },
  {
    "sn": 401472,
    "skillSn": 40147,
    "level": 2,
    "buffGroupSn": 4014,
    "order": 0,
    "grade": 2,
    "motifSn": 1,
    "line": [
      102
    ],
    "unlock": 0
  },
  {
    "sn": 401501,
    "skillSn": 40150,
    "level": 1,
    "buffGroupSn": 4014,
    "order": 0,
    "grade": 3,
    "motifSn": 1,
    "line": [
      102
    ],
    "unlock": 0
  },
  {
    "sn": 401551,
    "skillSn": 40155,
    "level": 1,
    "buffGroupSn": 4015,
    "order": 0,
    "grade": 1,
    "motifSn": 1,
    "line": [
      102
    ],
    "unlock": 0
  },
  {
    "sn": 401552,
    "skillSn": 40155,
    "level": 2,
    "buffGroupSn": 4015,
    "order": 0,
    "grade": 1,
    "motifSn": 1,
    "line": [
      102
    ],
    "unlock": 0
  },
  {
    "sn": 401553,
    "skillSn": 40155,
    "level": 3,
    "buffGroupSn": 4015,
    "order": 0,
    "grade": 1,
    "motifSn": 1,
    "line": [
      102
    ],
    "unlock": 0
  },
  {
    "sn": 401561,
    "skillSn": 40156,
    "level": 1,
    "buffGroupSn": 4015,
    "order": 0,
    "grade": 1,
    "motifSn": 1,
    "line": [
      102
    ],
    "unlock": 0
  },
  {
    "sn": 401562,
    "skillSn": 40156,
    "level": 2,
    "buffGroupSn": 4015,
    "order": 0,
    "grade": 1,
    "motifSn": 1,
    "line": [
      102
    ],
    "unlock": 0
  },
  {
    "sn": 401563,
    "skillSn": 40156,
    "level": 3,
    "buffGroupSn": 4015,
    "order": 0,
    "grade": 1,
    "motifSn": 1,
    "line": [
      102
    ],
    "unlock": 0
  },
  {
    "sn": 401571,
    "skillSn": 40157,
    "level": 1,
    "buffGroupSn": 4015,
    "order": 0,
    "grade": 1,
    "motifSn": 1,
    "line": [
      102
    ],
    "unlock": 0
  },
  {
    "sn": 401572,
    "skillSn": 40157,
    "level": 2,
    "buffGroupSn": 4015,
    "order": 0,
    "grade": 1,
    "motifSn": 1,
    "line": [
      102
    ],
    "unlock": 0
  },
  {
    "sn": 401573,
    "skillSn": 40157,
    "level": 3,
    "buffGroupSn": 4015,
    "order": 0,
    "grade": 1,
    "motifSn": 1,
    "line": [
      102
    ],
    "unlock": 0
  },
  {
    "sn": 401581,
    "skillSn": 40158,
    "level": 1,
    "buffGroupSn": 4015,
    "order": 0,
    "grade": 2,
    "motifSn": 1,
    "line": [
      102
    ],
    "unlock": 0
  },
  {
    "sn": 401582,
    "skillSn": 40158,
    "level": 2,
    "buffGroupSn": 4015,
    "order": 0,
    "grade": 2,
    "motifSn": 1,
    "line": [
      102
    ],
    "unlock": 0
  },
  {
    "sn": 401591,
    "skillSn": 40159,
    "level": 1,
    "buffGroupSn": 4015,
    "order": 0,
    "grade": 2,
    "motifSn": 1,
    "line": [
      102
    ],
    "unlock": 0
  },
  {
    "sn": 401592,
    "skillSn": 40159,
    "level": 2,
    "buffGroupSn": 4015,
    "order": 0,
    "grade": 2,
    "motifSn": 1,
    "line": [
      102
    ],
    "unlock": 0
  },
  {
    "sn": 401611,
    "skillSn": 40161,
    "level": 1,
    "buffGroupSn": 4015,
    "order": 0,
    "grade": 3,
    "motifSn": 1,
    "line": [
      102
    ],
    "unlock": 0
  },
  {
    "sn": 401641,
    "skillSn": 40164,
    "level": 1,
    "buffGroupSn": 4016,
    "order": 0,
    "grade": 1,
    "motifSn": 1,
    "line": [
      102
    ],
    "unlock": 0
  },
  {
    "sn": 401642,
    "skillSn": 40164,
    "level": 2,
    "buffGroupSn": 4016,
    "order": 0,
    "grade": 1,
    "motifSn": 1,
    "line": [
      102
    ],
    "unlock": 0
  },
  {
    "sn": 401643,
    "skillSn": 40164,
    "level": 3,
    "buffGroupSn": 4016,
    "order": 0,
    "grade": 1,
    "motifSn": 1,
    "line": [
      102
    ],
    "unlock": 0
  },
  {
    "sn": 401651,
    "skillSn": 40165,
    "level": 1,
    "buffGroupSn": 4016,
    "order": 0,
    "grade": 1,
    "motifSn": 1,
    "line": [
      102
    ],
    "unlock": 0
  },
  {
    "sn": 401652,
    "skillSn": 40165,
    "level": 2,
    "buffGroupSn": 4016,
    "order": 0,
    "grade": 1,
    "motifSn": 1,
    "line": [
      102
    ],
    "unlock": 0
  },
  {
    "sn": 401653,
    "skillSn": 40165,
    "level": 3,
    "buffGroupSn": 4016,
    "order": 0,
    "grade": 1,
    "motifSn": 1,
    "line": [
      102
    ],
    "unlock": 0
  },
  {
    "sn": 401661,
    "skillSn": 40166,
    "level": 1,
    "buffGroupSn": 4016,
    "order": 0,
    "grade": 1,
    "motifSn": 1,
    "line": [
      102
    ],
    "unlock": 0
  },
  {
    "sn": 401662,
    "skillSn": 40166,
    "level": 2,
    "buffGroupSn": 4016,
    "order": 0,
    "grade": 1,
    "motifSn": 1,
    "line": [
      102
    ],
    "unlock": 0
  },
  {
    "sn": 401663,
    "skillSn": 40166,
    "level": 3,
    "buffGroupSn": 4016,
    "order": 0,
    "grade": 1,
    "motifSn": 1,
    "line": [
      102
    ],
    "unlock": 0
  },
  {
    "sn": 401671,
    "skillSn": 40167,
    "level": 1,
    "buffGroupSn": 4016,
    "order": 0,
    "grade": 2,
    "motifSn": 1,
    "line": [
      102
    ],
    "unlock": 0
  },
  {
    "sn": 401672,
    "skillSn": 40167,
    "level": 2,
    "buffGroupSn": 4016,
    "order": 0,
    "grade": 2,
    "motifSn": 1,
    "line": [
      102
    ],
    "unlock": 0
  },
  {
    "sn": 401681,
    "skillSn": 40168,
    "level": 1,
    "buffGroupSn": 4016,
    "order": 0,
    "grade": 2,
    "motifSn": 1,
    "line": [
      102
    ],
    "unlock": 0
  },
  {
    "sn": 401682,
    "skillSn": 40168,
    "level": 2,
    "buffGroupSn": 4016,
    "order": 0,
    "grade": 2,
    "motifSn": 1,
    "line": [
      102
    ],
    "unlock": 0
  },
  {
    "sn": 401691,
    "skillSn": 40169,
    "level": 1,
    "buffGroupSn": 4016,
    "order": 0,
    "grade": 3,
    "motifSn": 1,
    "line": [
      102
    ],
    "unlock": 0
  },
  {
    "sn": 402391,
    "skillSn": 40239,
    "level": 1,
    "buffGroupSn": 4007,
    "order": 99,
    "grade": 1,
    "motifSn": 1,
    "line": [
      101
    ],
    "unlock": 0
  },
  {
    "sn": 402392,
    "skillSn": 40239,
    "level": 2,
    "buffGroupSn": 4007,
    "order": 100,
    "grade": 1,
    "motifSn": 1,
    "line": [
      101
    ],
    "unlock": 0
  },
  {
    "sn": 402393,
    "skillSn": 40239,
    "level": 3,
    "buffGroupSn": 4007,
    "order": 101,
    "grade": 1,
    "motifSn": 1,
    "line": [
      101
    ],
    "unlock": 0
  },
  {
    "sn": 402401,
    "skillSn": 40240,
    "level": 1,
    "buffGroupSn": 4007,
    "order": 102,
    "grade": 1,
    "motifSn": 1,
    "line": [
      101
    ],
    "unlock": 0
  },
  {
    "sn": 402402,
    "skillSn": 40240,
    "level": 2,
    "buffGroupSn": 4007,
    "order": 103,
    "grade": 1,
    "motifSn": 1,
    "line": [
      101
    ],
    "unlock": 0
  },
  {
    "sn": 402403,
    "skillSn": 40240,
    "level": 3,
    "buffGroupSn": 4007,
    "order": 104,
    "grade": 1,
    "motifSn": 1,
    "line": [
      101
    ],
    "unlock": 0
  },
  {
    "sn": 402411,
    "skillSn": 40241,
    "level": 1,
    "buffGroupSn": 4007,
    "order": 105,
    "grade": 1,
    "motifSn": 1,
    "line": [
      101
    ],
    "unlock": 0
  },
  {
    "sn": 402412,
    "skillSn": 40241,
    "level": 2,
    "buffGroupSn": 4007,
    "order": 106,
    "grade": 1,
    "motifSn": 1,
    "line": [
      101
    ],
    "unlock": 0
  },
  {
    "sn": 402413,
    "skillSn": 40241,
    "level": 3,
    "buffGroupSn": 4007,
    "order": 107,
    "grade": 1,
    "motifSn": 1,
    "line": [
      101
    ],
    "unlock": 0
  },
  {
    "sn": 402421,
    "skillSn": 40242,
    "level": 1,
    "buffGroupSn": 4007,
    "order": 108,
    "grade": 2,
    "motifSn": 1,
    "line": [
      101
    ],
    "unlock": 0
  },
  {
    "sn": 402422,
    "skillSn": 40242,
    "level": 2,
    "buffGroupSn": 4007,
    "order": 109,
    "grade": 2,
    "motifSn": 1,
    "line": [
      101
    ],
    "unlock": 0
  },
  {
    "sn": 402431,
    "skillSn": 40243,
    "level": 1,
    "buffGroupSn": 4007,
    "order": 110,
    "grade": 2,
    "motifSn": 1,
    "line": [
      101
    ],
    "unlock": 0
  },
  {
    "sn": 402432,
    "skillSn": 40243,
    "level": 2,
    "buffGroupSn": 4007,
    "order": 111,
    "grade": 2,
    "motifSn": 1,
    "line": [
      101
    ],
    "unlock": 0
  },
  {
    "sn": 402441,
    "skillSn": 40244,
    "level": 1,
    "buffGroupSn": 4007,
    "order": 112,
    "grade": 3,
    "motifSn": 1,
    "line": [
      101
    ],
    "unlock": 0
  },
  {
    "sn": 402831,
    "skillSn": 40283,
    "level": 1,
    "buffGroupSn": 4017,
    "order": 1,
    "grade": 1,
    "motifSn": 1,
    "line": [
      101
    ],
    "unlock": 0
  },
  {
    "sn": 402832,
    "skillSn": 40283,
    "level": 2,
    "buffGroupSn": 4017,
    "order": 2,
    "grade": 1,
    "motifSn": 1,
    "line": [
      101
    ],
    "unlock": 0
  },
  {
    "sn": 402833,
    "skillSn": 40283,
    "level": 3,
    "buffGroupSn": 4017,
    "order": 3,
    "grade": 1,
    "motifSn": 1,
    "line": [
      101
    ],
    "unlock": 0
  },
  {
    "sn": 402841,
    "skillSn": 40284,
    "level": 1,
    "buffGroupSn": 4017,
    "order": 4,
    "grade": 1,
    "motifSn": 1,
    "line": [
      101
    ],
    "unlock": 0
  },
  {
    "sn": 402842,
    "skillSn": 40284,
    "level": 2,
    "buffGroupSn": 4017,
    "order": 5,
    "grade": 1,
    "motifSn": 1,
    "line": [
      101
    ],
    "unlock": 0
  },
  {
    "sn": 402843,
    "skillSn": 40284,
    "level": 3,
    "buffGroupSn": 4017,
    "order": 6,
    "grade": 1,
    "motifSn": 1,
    "line": [
      101
    ],
    "unlock": 0
  },
  {
    "sn": 402851,
    "skillSn": 40285,
    "level": 1,
    "buffGroupSn": 4017,
    "order": 7,
    "grade": 1,
    "motifSn": 1,
    "line": [
      101
    ],
    "unlock": 0
  },
  {
    "sn": 402852,
    "skillSn": 40285,
    "level": 2,
    "buffGroupSn": 4017,
    "order": 8,
    "grade": 1,
    "motifSn": 1,
    "line": [
      101
    ],
    "unlock": 0
  },
  {
    "sn": 402853,
    "skillSn": 40285,
    "level": 3,
    "buffGroupSn": 4017,
    "order": 9,
    "grade": 1,
    "motifSn": 1,
    "line": [
      101
    ],
    "unlock": 0
  },
  {
    "sn": 402861,
    "skillSn": 40286,
    "level": 1,
    "buffGroupSn": 4017,
    "order": 10,
    "grade": 2,
    "motifSn": 1,
    "line": [
      101
    ],
    "unlock": 0
  },
  {
    "sn": 402862,
    "skillSn": 40286,
    "level": 2,
    "buffGroupSn": 4017,
    "order": 11,
    "grade": 2,
    "motifSn": 1,
    "line": [
      101
    ],
    "unlock": 0
  },
  {
    "sn": 402891,
    "skillSn": 40289,
    "level": 1,
    "buffGroupSn": 4017,
    "order": 12,
    "grade": 2,
    "motifSn": 1,
    "line": [
      101
    ],
    "unlock": 0
  },
  {
    "sn": 402892,
    "skillSn": 40289,
    "level": 2,
    "buffGroupSn": 4017,
    "order": 13,
    "grade": 2,
    "motifSn": 1,
    "line": [
      101
    ],
    "unlock": 0
  },
  {
    "sn": 402911,
    "skillSn": 40291,
    "level": 1,
    "buffGroupSn": 4017,
    "order": 14,
    "grade": 3,
    "motifSn": 1,
    "line": [
      101
    ],
    "unlock": 0
  },
  {
    "sn": 402951,
    "skillSn": 40295,
    "level": 1,
    "buffGroupSn": 4018,
    "order": 15,
    "grade": 1,
    "motifSn": 1,
    "line": [
      101
    ],
    "unlock": 0
  },
  {
    "sn": 402952,
    "skillSn": 40295,
    "level": 2,
    "buffGroupSn": 4018,
    "order": 16,
    "grade": 1,
    "motifSn": 1,
    "line": [
      101
    ],
    "unlock": 0
  },
  {
    "sn": 402953,
    "skillSn": 40295,
    "level": 3,
    "buffGroupSn": 4018,
    "order": 17,
    "grade": 1,
    "motifSn": 1,
    "line": [
      101
    ],
    "unlock": 0
  },
  {
    "sn": 402961,
    "skillSn": 40296,
    "level": 1,
    "buffGroupSn": 4018,
    "order": 18,
    "grade": 1,
    "motifSn": 1,
    "line": [
      101
    ],
    "unlock": 0
  },
  {
    "sn": 402962,
    "skillSn": 40296,
    "level": 2,
    "buffGroupSn": 4018,
    "order": 19,
    "grade": 1,
    "motifSn": 1,
    "line": [
      101
    ],
    "unlock": 0
  },
  {
    "sn": 402963,
    "skillSn": 40296,
    "level": 3,
    "buffGroupSn": 4018,
    "order": 20,
    "grade": 1,
    "motifSn": 1,
    "line": [
      101
    ],
    "unlock": 0
  },
  {
    "sn": 402971,
    "skillSn": 40297,
    "level": 1,
    "buffGroupSn": 4018,
    "order": 21,
    "grade": 1,
    "motifSn": 1,
    "line": [
      101
    ],
    "unlock": 0
  },
  {
    "sn": 402972,
    "skillSn": 40297,
    "level": 2,
    "buffGroupSn": 4018,
    "order": 22,
    "grade": 1,
    "motifSn": 1,
    "line": [
      101
    ],
    "unlock": 0
  },
  {
    "sn": 402973,
    "skillSn": 40297,
    "level": 3,
    "buffGroupSn": 4018,
    "order": 23,
    "grade": 1,
    "motifSn": 1,
    "line": [
      101
    ],
    "unlock": 0
  },
  {
    "sn": 402981,
    "skillSn": 40298,
    "level": 1,
    "buffGroupSn": 4018,
    "order": 24,
    "grade": 2,
    "motifSn": 1,
    "line": [
      101
    ],
    "unlock": 0
  },
  {
    "sn": 402982,
    "skillSn": 40298,
    "level": 2,
    "buffGroupSn": 4018,
    "order": 25,
    "grade": 2,
    "motifSn": 1,
    "line": [
      101
    ],
    "unlock": 0
  },
  {
    "sn": 402991,
    "skillSn": 40299,
    "level": 1,
    "buffGroupSn": 4018,
    "order": 26,
    "grade": 2,
    "motifSn": 1,
    "line": [
      101
    ],
    "unlock": 0
  },
  {
    "sn": 402992,
    "skillSn": 40299,
    "level": 2,
    "buffGroupSn": 4018,
    "order": 27,
    "grade": 2,
    "motifSn": 1,
    "line": [
      101
    ],
    "unlock": 0
  },
  {
    "sn": 403011,
    "skillSn": 40301,
    "level": 1,
    "buffGroupSn": 4018,
    "order": 28,
    "grade": 3,
    "motifSn": 1,
    "line": [
      101
    ],
    "unlock": 0
  }
]